Metadata-Version: 1.2
Name: cryptocompy2
Version: 0.1.1.1
Summary: Simple wrapper for the public Cryptocompare API.
Home-page: https://github.com/dannychua/cryptocompare2
Author: Danny Chua
Author-email: dannychua@somewhere.somewhere
License: MIT
Download-URL: https://github.com/dannychua/cryptocompy2/archive/0.1.1.1.tar.gz
Platform: UNKNOWN
Requires-Python: >=3
